{
  "content": [
    {
      "content": null,
      "created": "2022-06-12T00:13:10.300268Z",
      "format": null,
      "last_modified": "2022-06-12T00:11:30.134360Z",
      "mimetype": "application/json",
      "name": "coastline_cty_10km.geo.json",
      "path": "A_Python_Course/L2/res/world_geo.json_files/coastline_cty_10km.geo.json",
      "size": 485226,
      "type": "file",
      "writable": true
    }
  ],
  "created": "2022-06-12T00:13:10.300268Z",
  "format": "json",
  "last_modified": "2022-06-12T00:13:10.300268Z",
  "mimetype": null,
  "name": "world_geo.json_files",
  "path": "A_Python_Course/L2/res/world_geo.json_files",
  "size": null,
  "type": "directory",
  "writable": true
}